tbnpy/__init__.py
tbnpy/adaptiveMH.py
tbnpy/cpt.py
tbnpy/inference.py
tbnpy/variable.py
tbnpy-0.1.0.dist-info/licenses/LICENSE
tbnpy-0.1.0.dist-info/METADATA
tbnpy-0.1.0.dist-info/WHEEL
tbnpy-0.1.0.dist-info/top_level.txt
tbnpy-0.1.0.dist-info/RECORD
