Metadata-Version: 2.4
Name: tbnpy
Version: 0.1.0
Summary: Tensor-based Bayesian Network (TBN) toolkit for scalable probabilistic inference
Author: Ji-Eun Byun
License: MIT License
Project-URL: Homepage, https://github.com/jieunbyun/tbnpy
Project-URL: Documentation, https://jieunbyun.github.io/tbnpy/
Requires-Python: >=3.9
License-File: LICENSE
Requires-Dist: numpy>=1.23
Requires-Dist: torch>=2.0
Requires-Dist: pandas>=1.5
Requires-Dist: ndtools-duco>=0.1.5
Provides-Extra: dev
Requires-Dist: pytest>=7.0; extra == "dev"
Provides-Extra: docs
Requires-Dist: sphinx>=8; extra == "docs"
Requires-Dist: furo; extra == "docs"
Requires-Dist: myst-parser; extra == "docs"
Requires-Dist: sphinx-autodoc-typehints; extra == "docs"
Dynamic: license-file
